impit-0.9.2.dist-info/METADATA
impit-0.9.2.dist-info/WHEEL
impit.libs/libgcc_s-98a1ef30.so.1
impit/__init__.py
impit/cookies.py
impit/impit.cpython-310-x86_64-linux-gnu.so
impit/impit.pyi
impit/py.typed
impit-0.9.2.dist-info/RECORD
